[
    {
      "_id": 1,
      "category": "Documentation",
      "title": "Should You Invest In Internal Knowledge Base For Your Company?",
      "details": "Aliquam finibus augue ac diam euismod, nec con sectetur erat dignissim. Pellentesque.",
      "img": "https://docbase-react.b-cdn.net/images/blog/blog-1.png"
      
    },
    {
        "_id": 2,
        "category": "Design",
        "title": "After Microsoft Ignite, Keep The Learning Momentum Going",
        "details": "Aliquam finibus augue ac diam euismod, nec con sectetur erat dignissim. Pellentesque.",
        "img": "https://docbase-react.b-cdn.net/images/blog/blog-page-grid-3-1.png"
    },
    {
        "_id": 3,
        "category": "Documentation",
        "title": "All English MSDN And TechNet Forums Are Now Read-Only",
        "details": "Aliquam finibus augue ac diam euismod, nec con sectetur erat dignissim. Pellentesque.",
        "img": "https://docbase-react.b-cdn.net/images/blog/blog-page-grid-3-2.png"
        
    },
    {
        "_id": 4,
        "category": "Woocommerce",
        "title": "Microsoft Q&A Graduates To General Availability!",
        "details": "Aliquam finibus augue ac diam euismod, nec con sectetur erat dignissim. Pellentesque.",
        "img": "https://docbase-react.b-cdn.net/images/blog/blog-page-grid-3-3.png"
        
    },
    {
        "_id": 5,
        "category": "Documentation",
        "title": "Should You Invest In Internal Knowledge Base For Your Company?",
        "details": "Aliquam finibus augue ac diam euismod, nec con sectetur erat dignissim. Pellentesque.",
        "img": "https://docbase-react.b-cdn.net/images/blog/blog-page-grid-3-4.png"
        
    },
    {
        "_id": 6,
        "category": "FIx",
        "title": "Microsoft Q&A Is Now The Official Micro Soft Site To Support All The Qsn?",
        "details": "Aliquam finibus augue ac diam euismod, and and and nec con sectetur erat dignissim. Pellentesque.",
        "img": "https://docbase-react.b-cdn.net/images/blog/blog-1.png"
        
    },
    {
        "_id": 7,
        "category": "Ui Design",
        "title": "Should You Invest In Internal Knowledge Base For Your Company?",
        "details": "Aliquam finibus augue ac diam euismod, nec con sectetur erat dignissim. Pellentesque.",
        "img": "https://docbase-react.b-cdn.net/images/blog/blog-page-grid-3-6.png"
        
    },
    {
        "_id": 8,
        "category": "WordPress",
        "title": "Should You Invest In Internal Knowledge Base For Your Company?",
        "details": "Aliquam finibus augue ac diam euismod, nec con sectetur erat dignissim. Pellentesque.",
        "img": "https://docbase-react.b-cdn.net/images/blog/blog-page-grid-3-7.png"
        
    }
]